{"Nodes":[],"ExecutionTime":"2022-07-10T14:42:25.6337779Z","GenerationTime":"0001-01-01T00:00:00","PluginUserSpecFlowId":"262c2e1a-72f2-417c-b840-d0e2030f6483","CLIUserSpecFlowId":null,"ExecutionResults":[{"ContextType":"Scenario","FeatureFolderPath":"Features","FeatureTitle":"Basket","ScenarioTitle":"Adding item to basket","ScenarioArguments":[],"Status":"OK","StepResults":[{"Duration":"00:01:38.8776272","Status":"OK","Error":null,"Outputs":null},{"Duration":"00:00:00.1532702","Status":"OK","Error":null,"Outputs":null},{"Duration":"00:00:00.1200838","Status":"OK","Error":null,"Outputs":null},{"Duration":"00:00:00.0968879","Status":"OK","Error":null,"Outputs":null},{"Duration":"00:00:38.9602961","Status":"OK","Error":null,"Outputs":null}],"Outputs":null}],"StepReports":null}